Workbook

Sheet Cover
B2: User Acceptance Test (UAT) — ICC ERP: General Ledger
B3: GL-R1 ผังบัญชีร่วม · GL-R2 Source/Category/Voucher · GL-R3 Journal · GL-R4 หลายสกุลเงิน
B5: โครงการ | C5: ICC ERP Phase 1 (ICC Oracle R12 revision)
B6: โมดูล | C6: General Ledger (GL)
B7: Branch / Build | C7: gl-icc-r12-revision
B8: สภาพแวดล้อมทดสอบ | C8: http://localhost:5173 (ฐานข้อมูลทดสอบ icc_erp)
B9: ที่มาของ Scenario | C9: e2e tests: accounts, journals, currencies (apps/api/test)
B10: ข้อมูลทดสอบ | C10: ข้อมูลสังเคราะห์เท่านั้น ไม่ใช่ข้อมูลหรืออัตราจริง (P08)
B11: เวอร์ชันเอกสาร | C11: 1.0
B12: วันที่จัดทำ | C12: 46322.708
B13: ผู้ทดสอบหลัก
B14: ช่วงทดสอบ
B17: สรุปผลการทดสอบ
B18: สถานะ | C18: จำนวน | D18: ร้อยละ
B19: Not Run | C19: =COUNTIF('Test Cases'!$K$6:$K$77,B19) -> 72 | D19: =IF($C$23=0,0,C19/$C$23) -> 1
B20: Pass | C20: =COUNTIF('Test Cases'!$K$6:$K$77,B20) -> 0 | D20: =IF($C$23=0,0,C20/$C$23) -> 0
B21: Fail | C21: =COUNTIF('Test Cases'!$K$6:$K$77,B21) -> 0 | D21: =IF($C$23=0,0,C21/$C$23) -> 0
B22: Blocked | C22: =COUNTIF('Test Cases'!$K$6:$K$77,B22) -> 0 | D22: =IF($C$23=0,0,C22/$C$23) -> 0
B23: รวม Test Case | C23: =COUNTA('Test Cases'!$A$6:$A$77) -> 72 | D23: =IF(C23=0,0,SUM(C19:C22)/C23) -> 1
B25: วิธีใช้เอกสาร
B26: 1. ช่องสีเหลือง = ช่องที่ผู้ทดสอบกรอก (ผลจริง, สถานะ, ผู้ทดสอบ, วันที่ทดสอบ, Defect, หมายเหตุ)
B27: 2. สถานะเลือกจากรายการ: Not Run / Pass / Fail / Blocked — สรุปผลในหน้านี้และหน้า Scenarios คำนวณอัตโนมัติ
B28: 3. แถว EX-01 ในหน้า Test Cases เป็นตัวอย่างการกรอก ไม่นับในสรุปผล
B29: 4. Pre-condition อ้างถึงชุดข้อมูลในหน้า Test Data (TD-xx); วันที่ใช้รูปแบบ dd/mm/yyyy ปี ค.ศ.
B30: 5. เมื่อผลเป็น Fail ให้บันทึกเลข Defect และแนบภาพหน้าจอ แล้วทดสอบซ้ำหลังแก้ไข

Sheet Scenarios
A1: Test Scenarios — GL-R1 ถึง GL-R4
A2: จำนวนและผลนับจากหน้า Test Cases อัตโนมัติ
A4: Scenario ID | B4: รอบ | C4: Scenario | D4: หน้าจอ | E4: Priority | F4: Test Case | G4: Pass | H4: Fail | I4: Blocked | J4: Not Run
A5: SC-01 | B5: GL-R1 | C5: ผังบัญชีร่วม ICC/ITK แยกด้วยค่า Company | D5: S05 /settings/accounts | E5: High | F5: =COUNTIF('Test Cases'!$B$6:$B$77,A5) -> 4 | G5: =COUNTIFS('Test Cases'!$B$6:$B$77,$A5,'Test Cases'!$K$6:$K$77,"Pass") -> 0 | H5: =COUNTIFS('Test Cases'!$B$6:$B$77,$A5,'Test Cases'!$K$6:$K$77,"Fail") -> 0 | I5: =COUNTIFS('Test Cases'!$B$6:$B$77,$A5,'Test Cases'!$K$6:$K$77,"Blocked") -> 0 | J5: =COUNTIFS('Test Cases'!$B$6:$B$77,$A5,'Test Cases'!$K$6:$K$77,"Not Run") -> 4
A6: SC-02 | B6: GL-R1 | C6: ค่า Segment และคุณสมบัติ (นำเข้าซ้ำได้, ผิดแล้วไม่บันทึกทั้งชุด) | D6: S05 /settings/accounts | E6: High | F6: =COUNTIF('Test Cases'!$B$6:$B$77,A6) -> 3 | G6: =COUNTIFS('Test Cases'!$B$6:$B$77,$A6,'Test Cases'!$K$6:$K$77,"Pass") -> 0 | H6: =COUNTIFS('Test Cases'!$B$6:$B$77,$A6,'Test Cases'!$K$6:$K$77,"Fail") -> 0 | I6: =COUNTIFS('Test Cases'!$B$6:$B$77,$A6,'Test Cases'!$K$6:$K$77,"Blocked") -> 0 | J6: =COUNTIFS('Test Cases'!$B$6:$B$77,$A6,'Test Cases'!$K$6:$K$77,"Not Run") -> 3
A7: SC-03 | B7: GL-R1 | C7: สร้างบัญชี (Account combination) และ Cross-validation | D7: S05 แท็บ บัญชี (Combination) | E7: High | F7: =COUNTIF('Test Cases'!$B$6:$B$77,A7) -> 5 | G7: =COUNTIFS('Test Cases'!$B$6:$B$77,$A7,'Test Cases'!$K$6:$K$77,"Pass") -> 0 | H7: =COUNTIFS('Test Cases'!$B$6:$B$77,$A7,'Test Cases'!$K$6:$K$77,"Fail") -> 0 | I7: =COUNTIFS('Test Cases'!$B$6:$B$77,$A7,'Test Cases'!$K$6:$K$77,"Blocked") -> 0 | J7: =COUNTIFS('Test Cases'!$B$6:$B$77,$A7,'Test Cases'!$K$6:$K$77,"Not Run") -> 5
A8: SC-04 | B8: GL-R1 | C8: ตรวจบัญชีตอนลงบัญชี (บริษัทอื่น / ปิดใช้งาน / หมดอายุ) | D8: G03 /gl/journals | E8: High | F8: =COUNTIF('Test Cases'!$B$6:$B$77,A8) -> 4 | G8: =COUNTIFS('Test Cases'!$B$6:$B$77,$A8,'Test Cases'!$K$6:$K$77,"Pass") -> 0 | H8: =COUNTIFS('Test Cases'!$B$6:$B$77,$A8,'Test Cases'!$K$6:$K$77,"Fail") -> 0 | I8: =COUNTIFS('Test Cases'!$B$6:$B$77,$A8,'Test Cases'!$K$6:$K$77,"Blocked") -> 0 | J8: =COUNTIFS('Test Cases'!$B$6:$B$77,$A8,'Test Cases'!$K$6:$K$77,"Not Run") -> 4
A9: SC-05 | B9: GL-R1 | C9: ลำดับชั้นบัญชี (Parent / Child) | D9: S05 /settings/accounts | E9: Medium | F9: =COUNTIF('Test Cases'!$B$6:$B$77,A9) -> 2 | G9: =COUNTIFS('Test Cases'!$B$6:$B$77,$A9,'Test Cases'!$K$6:$K$77,"Pass") -> 0 | H9: =COUNTIFS('Test Cases'!$B$6:$B$77,$A9,'Test Cases'!$K$6:$K$77,"Fail") -> 0 | I9: =COUNTIFS('Test Cases'!$B$6:$B$77,$A9,'Test Cases'!$K$6:$K$77,"Blocked") -> 0 | J9: =COUNTIFS('Test Cases'!$B$6:$B$77,$A9,'Test Cases'!$K$6:$K$77,"Not Run") -> 2
A10: SC-06 | B10: GL-R1 | C10: ขอเปิดบัญชีใหม่ผ่านการอนุมัติ (GL-101) | D10: GL-101 /gl/account-requests, H02 /approvals | E10: High | F10: =COUNTIF('Test Cases'!$B$6:$B$77,A10) -> 4 | G10: =COUNTIFS('Test Cases'!$B$6:$B$77,$A10,'Test Cases'!$K$6:$K$77,"Pass") -> 0 | H10: =COUNTIFS('Test Cases'!$B$6:$B$77,$A10,'Test Cases'!$K$6:$K$77,"Fail") -> 0 | I10: =COUNTIFS('Test Cases'!$B$6:$B$77,$A10,'Test Cases'!$K$6:$K$77,"Blocked") -> 0 | J10: =COUNTIFS('Test Cases'!$B$6:$B$77,$A10,'Test Cases'!$K$6:$K$77,"Not Run") -> 4
A11: SC-07 | B11: GL-R1 | C11: โครงสร้าง ICC 8 segment (57 หลัก) และค่าเริ่มต้น | D11: S05 /settings/accounts | E11: High | F11: =COUNTIF('Test Cases'!$B$6:$B$77,A11) -> 4 | G11: =COUNTIFS('Test Cases'!$B$6:$B$77,$A11,'Test Cases'!$K$6:$K$77,"Pass") -> 0 | H11: =COUNTIFS('Test Cases'!$B$6:$B$77,$A11,'Test Cases'!$K$6:$K$77,"Fail") -> 0 | I11: =COUNTIFS('Test Cases'!$B$6:$B$77,$A11,'Test Cases'!$K$6:$K$77,"Blocked") -> 0 | J11: =COUNTIFS('Test Cases'!$B$6:$B$77,$A11,'Test Cases'!$K$6:$K$77,"Not Run") -> 4
A12: SC-08 | B12: GL-R1 | C12: สิทธิ์ดูแลผังบัญชี (System Admin เท่านั้น) | D12: S05 /settings/accounts | E12: Medium | F12: =COUNTIF('Test Cases'!$B$6:$B$77,A12) -> 1 | G12: =COUNTIFS('Test Cases'!$B$6:$B$77,$A12,'Test Cases'!$K$6:$K$77,"Pass") -> 0 | H12: =COUNTIFS('Test Cases'!$B$6:$B$77,$A12,'Test Cases'!$K$6:$K$77,"Fail") -> 0 | I12: =COUNTIFS('Test Cases'!$B$6:$B$77,$A12,'Test Cases'!$K$6:$K$77,"Blocked") -> 0 | J12: =COUNTIFS('Test Cases'!$B$6:$B$77,$A12,'Test Cases'!$K$6:$K$77,"Not Run") -> 1
A13: SC-09 | B13: GL-R3 | C13: บันทึก Journal และตรวจตอน Complete | D13: G03 /gl/journals | E13: High | F13: =COUNTIF('Test Cases'!$B$6:$B$77,A13) -> 3 | G13: =COUNTIFS('Test Cases'!$B$6:$B$77,$A13,'Test Cases'!$K$6:$K$77,"Pass") -> 0 | H13: =COUNTIFS('Test Cases'!$B$6:$B$77,$A13,'Test Cases'!$K$6:$K$77,"Fail") -> 0 | I13: =COUNTIFS('Test Cases'!$B$6:$B$77,$A13,'Test Cases'!$K$6:$K$77,"Blocked") -> 0 | J13: =COUNTIFS('Test Cases'!$B$6:$B$77,$A13,'Test Cases'!$K$6:$K$77,"Not Run") -> 3
A14: SC-10 | B14: GL-R3 | C14: Journal กับสถานะงวดบัญชี | D14: G03 /gl/journals, S04 /gl/periods | E14: High | F14: =COUNTIF('Test Cases'!$B$6:$B$77,A14) -> 2 | G14: =COUNTIFS('Test Cases'!$B$6:$B$77,$A14,'Test Cases'!$K$6:$K$77,"Pass") -> 0 | H14: =COUNTIFS('Test Cases'!$B$6:$B$77,$A14,'Test Cases'!$K$6:$K$77,"Fail") -> 0 | I14: =COUNTIFS('Test Cases'!$B$6:$B$77,$A14,'Test Cases'!$K$6:$K$77,"Blocked") -> 0 | J14: =COUNTIFS('Test Cases'!$B$6:$B$77,$A14,'Test Cases'!$K$6:$K$77,"Not Run") -> 2
A15: SC-11 | B15: GL-R3 | C15: วงจร Journal: อนุมัติ, Post โดยผู้ตรวจสอบ, ห้ามแก้หลัง Post | D15: G03 /gl/journals, H02 /approvals | E15: High | F15: =COUNTIF('Test Cases'!$B$6:$B$77,A15) -> 7 | G15: =COUNTIFS('Test Cases'!$B$6:$B$77,$A15,'Test Cases'!$K$6:$K$77,"Pass") -> 0 | H15: =COUNTIFS('Test Cases'!$B$6:$B$77,$A15,'Test Cases'!$K$6:$K$77,"Fail") -> 0 | I15: =COUNTIFS('Test Cases'!$B$6:$B$77,$A15,'Test Cases'!$K$6:$K$77,"Blocked") -> 0 | J15: =COUNTIFS('Test Cases'!$B$6:$B$77,$A15,'Test Cases'!$K$6:$K$77,"Not Run") -> 7
A16: SC-12 | B16: GL-R2 | C16: กลับรายการ (Reversal / AutoReverse) | D16: G05 /gl/journals?status=posted | E16: High | F16: =COUNTIF('Test Cases'!$B$6:$B$77,A16) -> 3 | G16: =COUNTIFS('Test Cases'!$B$6:$B$77,$A16,'Test Cases'!$K$6:$K$77,"Pass") -> 0 | H16: =COUNTIFS('Test Cases'!$B$6:$B$77,$A16,'Test Cases'!$K$6:$K$77,"Fail") -> 0 | I16: =COUNTIFS('Test Cases'!$B$6:$B$77,$A16,'Test Cases'!$K$6:$K$77,"Blocked") -> 0 | J16: =COUNTIFS('Test Cases'!$B$6:$B$77,$A16,'Test Cases'!$K$6:$K$77,"Not Run") -> 3
... A23: SC-19 | B23: GL-R4 | C23: ปรับมูลค่าปลายงวด (Revaluation) และกลับรายการต้นงวดถัดไป | D23: GL-R4 /gl/currencies, CL04 /gl/trial-balance | E23: High | F23: =COUNTIF('Test Cases'!$B$6:$B$77,A23) -> 3 | G23: =COUNTIFS('Test Cases'!$B$6:$B$77,$A23,'Test Cases'!$K$6:$K$77,"Pass") -> 0 | H23: =COUNTIFS('Test Cases'!$B$6:$B$77,$A23,'Test Cases'!$K$6:$K$77,"Fail") -> 0 | I23: =COUNTIFS('Test Cases'!$B$6:$B$77,$A23,'Test Cases'!$K$6:$K$77,"Blocked") -> 0 | J23: =COUNTIFS('Test Cases'!$B$6:$B$77,$A23,'Test Cases'!$K$6:$K$77,"Not Run") -> 3
C24: รวม | F24: =SUM(F5:F23) -> 72 | G24: =SUM(G5:G23) -> 0 | H24: =SUM(H5:H23) -> 0 | I24: =SUM(I5:I23) -> 0 | J24: =SUM(J5:J23) -> 72

Sheet Test Cases
A1: Test Cases — GL-R1 ถึง GL-R4
A2: ช่องสีเหลืองให้ผู้ทดสอบกรอก · สถานะเลือกจากรายการ · แถว EX-01 เป็นตัวอย่าง ไม่นับในสรุป
A4: TC ID | B4: Scenario | C4: Test Case | D4: Pre-condition | E4: ขั้นตอนการทดสอบ | F4: ข้อมูลทดสอบ | G4: ผลที่คาดหวัง | H4: ผลที่ได้จริง | I4: Priority | J4: ผู้ทดสอบ | K4: สถานะ | L4: วันที่ทดสอบ | M4: Defect ID | N4: ทดสอบซ้ำ | O4: หมายเหตุ
A5: EX-01 | B5: SC-00 | C5: ตัวอย่างการกรอก | D5: ล็อกอินแล้ว | E5: 1. เปิดหน้าจอ 2. กดปุ่ม | F5: ค่าทดสอบ | G5: ระบบแสดงผลตามที่กำหนด | H5: แสดงผลถูกต้องตามที่คาด | I5: High | J5: สมชาย ท. | K5: Pass | L5: 46327.708 | O5: แนบภาพหน้าจอ EX-01.png
A6: TC-01-01 | B6: SC-01 | C6: ผูก ICC และ ITK กับผังบัญชีเดียวกัน คนละค่า Company | D6: ล็อกอินเป็น System Admin; มีบริษัท ICC และ ITK | E6: 1. เปิด S05 เลือกบริษัท ICC 2. สร้างผังบัญชี ICC_AFF ตามโครงสร้าง TD-01 ผูก ICC ค่า Company = 10 3. เพิ่มบริษัท ITK เข้าผังเดียวกัน ค่า Company = 20 4. สลับบริษัทเป็น ITK แล้วดูแท็บผังบัญชี | F6: ผัง ICC_AFF, segment CO/CC/ACC, ICC=10, ITK=20 | G6: ทั้ง ICC และ ITK เห็นผัง ICC_AFF ผังเดียวกัน แสดง "ใช้ร่วม: ICC = 10, ITK = 20" และ segment เรียง CO, CC, ACC | I6: High | K6: Not Run
A7: TC-01-02 | B7: SC-01 | C7: ค่า Company ซ้ำกับบริษัทอื่นในผังเดียวกัน | D7: ทำ TC-01-01 แล้ว; มีบริษัทที่สาม ZZ | E7: 1. เพิ่มบริษัท ZZ เข้าผัง ICC_AFF ด้วยค่า Company = 20 | F7: ZZ = 20 | G7: ระบบไม่ยอม แจ้งว่าค่า Company ถูกใช้แล้ว (COMPANY_VALUE_TAKEN) | I7: High | K7: Not Run
A8: TC-01-03 | B8: SC-01 | C8: บริษัทที่มีผังแล้วสร้างผังใหม่ไม่ได้ | D8: ทำ TC-01-01 แล้ว | E8: 1. สร้างผังใหม่รหัส OTHER ผูก ICC ค่า Company = 10 | F8: ผัง OTHER | G8: ระบบไม่ยอม แจ้งว่าบริษัทมีผังบัญชีแล้ว (COMPANY_HAS_CHART) | I8: High | K8: Not Run
A9: TC-01-04 | B9: SC-01 | C9: ผังต้องมี segment ป้าย Natural account | D9: ล็อกอินเป็น System Admin | E9: 1. สร้างผังใหม่ ใส่เฉพาะ segment CO และ CC (ไม่มีป้าย Natural account) 2. กดบันทึก | F9: ผัง ZZ | G9: ระบบไม่ยอม แจ้งที่ช่อง Segment ว่าต้องมีป้าย Natural account | I9: High | K9: Not Run
A10: TC-02-01 | B10: SC-02 | C10: บันทึกค่าเดิมซ้ำ นับเฉพาะที่เปลี่ยน | D10: ทำ TC-01-01 แล้ว และเพิ่มค่าตาม TD-01 | E10: 1. บันทึกค่า 110100 (ไม่เปลี่ยน) และ 410100 โดยเปลี่ยนคำอธิบายเป็น "รายได้จากการขาย" | F10: 110100 เงินสด, 410100 รายได้จากการขาย | G10: ผลลัพธ์: สร้างใหม่ 0, แก้ไข 1, ไม่เปลี่ยน 1 | I10: High | K10: Not Run
A11: TC-02-02 | B11: SC-02 | C11: ชุดค่าที่มีข้อผิดพลาด ไม่บันทึกเลยแม้แต่ค่าที่ถูก | D11: ทำ TC-01-01 แล้ว | E11: 1. บันทึกค่าพร้อมกัน 6 รายการตามข้อมูลทดสอบ 2. ดูรายการค่าของ ACC | F11: 510100 ต้นทุนขาย (ถูก) 1234567 (ยาว 7 เกิน 6) segment NOPE (ไม่มี) 999999 ไม่ระบุประเภทบัญชี 500000 หัวรวมแต่อนุญาตลงบัญชี 510200 วันสิ้นสุด 01/01/2027 ก่อนวันเริ่ม 01/02/2027 | G11: ระบบไม่บันทึกทั้งชุด แจ้งข้อผิดพลาดรายแถว: แถว 2 ค่า, แถว 3 segment, แถว 4 ประเภทบัญชี, แถว 5 อนุญาตลงบัญชี, แถว 6 วันสิ้นสุด; 510100 ไม่ถูกเพิ่ม | I11: High | K11: Not Run
A12: TC-02-03 | B12: SC-02 | C12: คุณสมบัติของค่าบัญชีแสดงครบ | D12: ทำ TC-01-01 แล้ว | E12: 1. ดูรายการค่าของ segment ACC | F12: 110100 Cash (กระทบยอด), 410100 attribute monthly_income = DIV-IN | G12: 110100 แสดงชื่ออังกฤษ Cash, กระทบยอด = ใช่, ตั้งงบได้, ไม่ใช่หัวรวม, ลงบัญชีได้; 410100 แสดง attribute monthly_income = DIV-IN | I12: High | K12: Not Run
A13: TC-03-01 | B13: SC-03 | C13: สร้างบัญชีของบริษัทตัวเอง และกันบัญชีซ้ำ | D13: ทำ TC-01-01 แล้ว | E13: 1. แท็บ บัญชี (Combination) บริษัท ICC กด + สร้างบัญชี 2. ใส่ 10-100-410100 กดสร้าง 3. สร้าง 10-100-410100 ซ้ำอีกครั้ง | F13: 10-100-410100 | G13: ครั้งแรกสร้างได้ ครั้งที่สองระบบแจ้งว่ามีบัญชีนี้แล้ว | I13: High | K13: Not Run
A14: TC-03-02 | B14: SC-03 | C14: ใช้ค่า Company ของบริษัทอื่นไม่ได้ | D14: ทำ TC-01-01 แล้ว | E14: 1. บริษัท ICC สร้าง 20-100-410100 2. สลับเป็น ITK สร้าง 20-100-410100 | F14: 20-100-410100 | G14: ICC: แจ้งว่าค่า Company ไม่ตรงกับบริษัท; ITK: สร้างได้ (ใช้ natural account เดียวกัน) | I14: High | K14: Not Run
A15: TC-03-03 | B15: SC-03 | C15: ค่าที่ไม่มีในผัง หรือ segment ไม่ครบ | D15: ทำ TC-01-01 แล้ว | E15: 1. สร้าง 10-100-999999 2. สร้าง 10-100 | F15: 10-100-999999, 10-100 | G15: ทั้งสองกรณีระบบไม่ยอม: ค่า 999999 ไม่มีในผัง / segment ไม่ครบ | I15: High | K15: Not Run
A16: TC-03-04 | B16: SC-03 | C16: ค่าที่ปิดใช้งานสร้างบัญชีไม่ได้ | D16: ทำ TC-01-01 แล้ว | E16: 1. ปิดใช้งานค่า CC = 000 2. สร้าง 10-000-110100 | F16: CC 000 ปิดใช้งาน | G16: ระบบแจ้งว่าค่านี้ปิดใช้งาน | I16: High | K16: Not Run
A17: TC-03-05 | B17: SC-03 | C17: กฎ Cross-validation | D17: ทำ TC-01-01 แล้ว; เพิ่มค่า CC 200 ผลิต | E17: 1. กด + กฎ Cross-validation: ถ้า ACC = 410100 ต้องใช้ CC = 100 2. สร้าง 10-200-410100 3. สร้าง 10-200-110100 | F17: ข้อความ: "บัญชีรายได้ต้องใช้ศูนย์ต้นทุนฝ่ายขาย" | G17: ข้อ 2 ไม่ยอม แสดงข้อความ "บัญชีรายได้ต้องใช้ศูนย์ต้นทุนฝ่ายขาย"; ข้อ 3 สร้างได้ | I17: High | K17: Not Run
... A22: TC-05-01 | B22: SC-05 | C22: กำหนดช่วงลูกให้หัวรวม แล้วดูต้นไม้ | D22: เพิ่มค่าหัวรวม 100000, 110000 และค่า 110200 | E22: 1. หัวรวม 110000: ช่วงลูก 110100–110199, 110200–110299 2. หัวรวม 100000: ช่วงหัวรวม 110000–119999 3. ดูลำดับชั้นของ 100000 | F22: 100000 สินทรัพย์ › 110000 เงินสดฯ › 110100, 110200 | G22: 100000 มีลูกเป็นหัวรวม 110000 และบัญชีปลายทาง 110100, 110200 | I22: Medium | K22: Not Run
A23: TC-05-02 | B23: SC-05 | C23: กันวงวน และกันการตั้งลูกให้ค่าที่ไม่ใช่หัวรวม | D23: ทำ TC-05-01 แล้ว | E23: 1. หัวรวม 110000 ใส่ช่วงหัวรวม 100000–100000 2. ค่า 110100 ใส่ช่วงลูก 110200 | G23: ข้อ 1 แจ้งว่าเกิดวงวนในลำดับชั้น; ข้อ 2 แจ้งว่า 110100 ไม่ใช่หัวรวม | I23: Medium | K23: Not Run
A24: TC-06-01 | B24: SC-06 | C24: คำขอเปิดบัญชีต้องระบุประเภทบัญชี | D24: Workflow GL_ACCOUNT_REQUEST 1 ขั้น (gl_accountant); ผู้ขอ gl.clerk และผู้อนุมัติ gl.manager มีสิทธิ์ gl_accountant ของ ICC | E24: 1. ล็อกอิน gl.clerk เปิด GL-101 สร้างคำขอ ACC 520100 ไม่เลือกประเภทบัญชี | F24: เหตุผล: เปิดบัญชีค่าโฆษณาออนไลน์ | G24: แจ้งที่ช่องประเภทบัญชีของแถวแรก | I24: High | K24: Not Run
A25: TC-06-02 | B25: SC-06 | C25: ส่งคำขอ ผังยังไม่เปลี่ยนจนกว่าจะอนุมัติ | D25: ต่อจาก TC-06-01 | E25: 1. เลือกประเภท = ค่าใช้จ่าย แล้วส่งคำขอ 2. ดูค่าของ ACC ใน S05 | F25: 520100 ค่าโฆษณาออนไลน์ (expense) | G25: คำขอสถานะ รออนุมัติ; ค่าของ ACC ยังมีแค่ 110100, 410100 | I25: High | K25: Not Run
A26: TC-06-03 | B26: SC-06 | C26: ผู้ขออนุมัติคำขอของตัวเองไม่ได้ (D07) | D26: ต่อจาก TC-06-02 | E26: 1. gl.clerk เปิด H02 Approval Inbox กดอนุมัติคำขอของตัวเอง | G26: ระบบไม่ยอม (ห้ามอนุมัติเอกสารของตัวเอง) | I26: High | K26: Not Run
A27: TC-06-04 | B27: SC-06 | C27: ผู้จัดการอนุมัติ ค่าใหม่เข้าผัง | D27: ต่อจาก TC-06-03 | E27: 1. ล็อกอิน gl.manager อนุมัติใน H02 2. gl.clerk เปิดคำขอใน GL-101 3. ดูค่าของ ACC ใน S05 | G27: คำขอสถานะ ใช้แล้ว (สร้าง 1); ค่าของ ACC เป็น 110100, 410100, 520100 | I27: High | K27: Not Run
A28: TC-07-01 | B28: SC-07 | C28: ค่าเริ่มต้นยาวเกินความยาว segment | D28: ล็อกอินเป็น System Admin; บริษัท ICC ยังไม่มีผัง | E28: 1. สร้างผัง กดปุ่ม "ใช้โครงสร้าง ICC 8 segment (57 หลัก)" 2. แก้ค่าเริ่มต้น RES1 เป็น 0000 3. กดบันทึก | F28: RES1 default = 0000 (ยาว 3) | G28: แจ้งที่ค่าเริ่มต้นของ RES1 ว่ายาวเกิน | I28: High | K28: Not Run
A29: TC-07-02 | B29: SC-07 | C29: สร้างผัง ICC 8 segment 57 หลัก | D29: ต่อจาก TC-07-01 | E29: 1. แก้ RES1 กลับเป็น 000, ใส่ค่าเริ่มต้น PROD = 0 2. ผูก ICC ค่า Company = ICC แล้วบันทึก 3. ดูตาราง segment | F29: TD-02 | G29: ผังมี 8 segment: CO 4, DEPT 6, ACC 9, PROD 25, IC 4, RES1–3 อย่างละ 3 รวม 57 หลัก; ค่าเริ่มต้น PROD=0, IC=0000, RES1–3=000 | I29: High | K29: Not Run
A30: TC-07-03 | B30: SC-07 | C30: ค่า Product มีเว้นวรรคได้ แต่ห้ามอักขระพิเศษ | D30: ต่อจาก TC-07-02 และเพิ่มค่าตาม TD-02 | E30: 1. เพิ่มค่า PROD "TEST BRAND A" 2. เพิ่มค่า PROD " LEADING" (มีช่องว่างหน้า) 3. เพิ่มค่า PROD "A-B" | F30: TEST BRAND A, " LEADING", A-B | G30: ข้อ 1 บันทึกได้ (คงช่องว่างด้านใน); ข้อ 2 บันทึกเป็น "LEADING"; ข้อ 3 ไม่ยอมที่ช่องค่า | I30: High | K30: Not Run
A31: TC-07-04 | B31: SC-07 | C31: เว้น segment ที่มีค่าเริ่มต้น ระบบเติมให้ | D31: ต่อจาก TC-07-03 | E31: 1. สร้างบัญชี ICC-T00001-900000001-TEST BRAND A---- 2. สร้างบัญชี ICC-T00001-900000001----- 3. สร้างบัญชี ICC--900000001----- (เว้น DEPT) | G31: ข้อ 1 ได้ ICC-T00001-900000001-TEST BRAND A-0000-000-000-000; ข้อ 2 ได้ (PROD = 0); ข้อ 3 แจ้งว่าต้องระบุ segment (DEPT ไม่มีค่าเริ่มต้น) | I31: High | K31: Not Run
A32: TC-08-01 | B32: SC-08 | C32: ผู้ใช้ทั่วไปแก้ผังบัญชีไม่ได้ | D32: ผู้ใช้ clerk ไม่ใช่ System Admin | E32: 1. ล็อกอิน clerk เปิด S05 ลองสร้างผัง และสร้างบัญชี 10-100-110100 | G32: ระบบไม่ให้เข้า/ไม่ยอมทำรายการ (ไม่มีสิทธิ์) | I32: Medium | K32: Not Run
A33: TC-09-01 | B33: SC-09 | C33: บันทึกร่างที่ยังไม่สมดุลได้ แต่ Complete ไม่ได้ | D33: ICC มีผังทดสอบ (TD-01), ปฏิทิน FY2027 เปิดงวด ม.ค.–ก.พ. 2027, กฎเลข JV{FY2}-{SEQ:6}, Workflow GL_JOURNAL 1 ขั้น (gl_accountant); ล็อกอินเป็น ผู้จัดทำ (Maker: gl_accountant) | E33: 1. G03 กด Journal ใหม่ ประเภท ปรับปรุง วันที่ 15/01/2027 2. ใส่บรรทัดตามข้อมูล แล้วกด บันทึกร่าง 3. กด Complete | F33: บรรทัด 1: 10-5100 Dr 100.00 บรรทัด 2: 10-1100 Dr 50.00 Cr 40.00 บรรทัด 3: 10-1100 Cr 50.00 | G33: บันทึกร่างได้ สถานะ Incomplete ยังไม่มีเลข ยอด Dr 150.00 / Cr 90.00; Complete แจ้งบรรทัด 2 ใส่ทั้งสองฝั่ง และ Journal ไม่สมดุล | I33: High | K33: Not Run
A34: TC-09-02 | B34: SC-09 | C34: บัญชีหัวรวม / ปิดใช้งาน / บริษัทอื่น แจ้งรายบรรทัด | D34: ต่อจาก TC-09-01; ITK มีผังและบัญชีของตัวเอง | E34: 1. สร้าง Journal ใหม่ตามข้อมูล 2. กด Complete | F34: บรรทัด 1: 10-5000 (หัวรวม) Dr 10 บรรทัด 2: 10-5900 (ปิดใช้งาน) Dr 10 บรรทัด 3: 20-5100 (ITK) Dr 10 บรรทัด 4: 10-1100 Cr 30 | G34: แจ้ง บรรทัด 1 บัญชีหัวรวม, บรรทัด 2 บัญชีปิดใช้งาน, บรรทัด 3 บัญชีบริษัทอื่น | I34: High | K34: Not Run
A35: TC-09-03 | B35: SC-09 | C35: ตรวจ Control Total | D35: ต่อจาก TC-09-01 | E35: 1. สร้าง Journal ใส่ Control Total 100.00 และบรรทัดยอด 90.00 2. กด Complete | F35: Control Total 100.00; 10-5100 Dr 90 / 10-1100 Cr 90 | G35: แจ้งที่ช่อง Control Total ว่ายอดไม่ตรง | I35: High | K35: Not Run
A36: TC-10-01 | B36: SC-10 | C36: งวด Future entry: Complete ได้ แต่ Post ไม่ได้ | D36: ICC มีผังทดสอบ (TD-01), ปฏิทิน FY2027 เปิดงวด ม.ค.–ก.พ. 2027, กฎเลข JV{FY2}-{SEQ:6}, Workflow GL_JOURNAL 1 ขั้น (gl_accountant); มี.ค. 2027 = Future entry | E36: 1. สร้าง Journal วันที่ 10/03/2027 กด Complete 2. Submit และให้ผู้จัดการอนุมัติ 3. ผู้จัดการกด Post | F36: 10-5100 Dr 10 / 10-1100 Cr 10 | G36: Complete ได้เลข JV27-000001; Post แจ้งว่างวดยังไม่เปิด | I36: High | K36: Not Run
A37: TC-10-02 | B37: SC-10 | C37: งวดที่ยังไม่เปิด Complete ไม่ได้ | D37: เม.ย. 2027 ยังไม่เปิด | E37: 1. สร้าง Journal วันที่ 01/04/2027 กด Complete | F37: 10-5100 Dr 10 / 10-1100 Cr 10 | G37: แจ้งว่างวดยังไม่เปิด | I37: High | K37: Not Run
A38: TC-11-01 | B38: SC-11 | C38: Complete ได้เลข Journal | D38: ICC มีผังทดสอบ (TD-01), ปฏิทิน FY2027 เปิดงวด ม.ค.–ก.พ. 2027, กฎเลข JV{FY2}-{SEQ:6}, Workflow GL_JOURNAL 1 ขั้น (gl_accountant); ล็อกอินเป็น ผู้จัดทำ (Maker: gl_accountant) | E38: 1. สร้าง Journal 15/01/2027 กด Complete | F38: 10-5100 Dr 1,234.50 / 10-1100 Cr 1,234.50 | G38: สถานะ Unposted เลข JV27-000001 | I38: High | K38: Not Run
A39: TC-11-02 | B39: SC-11 | C39: Post ก่อนอนุมัติไม่ได้ (P17) | D39: ต่อจาก TC-11-01 | E39: 1. ล็อกอินเป็น ผู้จัดการ (Manager: gl_accountant + gl_reviewer) กด Post | G39: แจ้งว่า Journal ยังไม่พร้อม Post | I39: High | K39: Not Run
A40: TC-11-03 | B40: SC-11 | C40: ผู้จัดทำอนุมัติเองไม่ได้ | D40: ต่อจาก TC-11-02 | E40: 1. ผู้จัดทำกด Submit 2. ผู้จัดทำเปิด H02 กดอนุมัติ | G40: สถานะ รออนุมัติ; การอนุมัติเองถูกปฏิเสธ (SELF_APPROVAL) | I40: High | K40: Not Run
A41: TC-11-04 | B41: SC-11 | C41: อนุมัติแล้ว Post ครั้งเดียว แม้กดซ้ำ | D41: ต่อจาก TC-11-03 | E41: 1. ผู้จัดการอนุมัติใน H02 2. ผู้จัดการกด Post สองครั้งติดกัน (หรือเปิดสองแท็บ) 3. เปิด CL04 งบทดลอง งวด FY2027-01 | G41: Post สำเร็จครั้งเดียว ไม่มีรายการซ้ำ; งบทดลอง 10-1100 Cr 1,234.50 ยอด -1,234.50, 10-5100 Dr 1,234.50; รวม Dr = Cr = 1,234.50 | I41: High | K41: Not Run
A42: TC-11-05 | B42: SC-11 | C42: Journal ที่ Post แล้วแก้/ลบไม่ได้ | D42: ต่อจาก TC-11-04 | E42: 1. เปิด Journal ที่ Post แล้ว ลองแก้คำอธิบาย 2. ลองลบ | G42: แก้และลบไม่ได้ | I42: High | K42: Not Run
A43: TC-11-06 | B43: SC-11 | C43: แก้หลัง Submit กลับเป็น Incomplete และยกเลิกการอนุมัติเดิม | D43: ICC มีผังทดสอบ (TD-01), ปฏิทิน FY2027 เปิดงวด ม.ค.–ก.พ. 2027, กฎเลข JV{FY2}-{SEQ:6}, Workflow GL_JOURNAL 1 ขั้น (gl_accountant) | E43: 1. สร้าง Journal, Complete, Submit 2. แก้วันที่เป็น 20/01/2027 และคำอธิบาย แล้วบันทึก 3. ผู้จัดการลองอนุมัติรายการเดิมใน H02 4. ลองลบ Journal นี้ 5. สร้างร่างใหม่แล้วลบ | F43: 10-5100 Dr 10 / 10-1100 Cr 10 | G43: หลังแก้: สถานะ Incomplete เลขเดิม JV27-000001 การอนุมัติหายไป; ข้อ 3 แจ้งว่าการอนุมัติไม่อยู่ในสถานะรอ; ข้อ 4 ลบไม่ได้ (เคย Submit แล้ว); ข้อ 5 ลบร่างได้ | I43: High | K43: Not Run
A44: TC-11-07 | B44: SC-11 | C44: Post ได้เฉพาะผู้ตรวจสอบที่ไม่ใช่ผู้จัดทำ (GL-201) | D44: Journal อนุมัติแล้ว สถานะ พร้อม Post | E44: 1. ผู้จัดทำ (ไม่มี gl_reviewer) กด Post 2. Admin ให้ผู้จัดทำมี gl_reviewer แล้วกด Post อีกครั้ง 3. ผู้จัดการกด Post | G44: ข้อ 1 ไม่มีสิทธิ์; ข้อ 2 ห้าม Post รายการที่ตัวเองจัดทำ (SELF_POST); ข้อ 3 Post สำเร็จ | I44: High | K44: Not Run
A45: TC-12-01 | B45: SC-12 | C45: กลับรายการครั้งเดียว สลับ Dr/Cr ตามวันที่เลือก | D45: Journal Post แล้ว: 10-5100 Dr 300 / 10-1100 Cr 300 | E45: 1. เปิด Journal ที่ Post แล้ว กด กลับรายการ วันที่ 05/02/2027 2. กลับรายการ Journal เดิมซ้ำ วันที่ 06/02/2027 3. กลับรายการของ Journal กลับรายการ | F45: วันที่กลับรายการ 05/02/2027 | G45: ได้ Journal ใหม่ Unposted เลข JV27-000002 วันที่ 05/02/2027 บรรทัด 10-5100 Cr 300, 10-1100 Dr 300; ข้อ 2 แจ้งว่ากลับรายการแล้ว; ข้อ 3 ไม่ยอม | I45: High | K45: Not Run
A46: TC-12-02 | B46: SC-12 | C46: ประเภทค้างจ่าย (ACCRUAL) กลับรายการอัตโนมัติงวดถัดไป | D46: ICC มีผังทดสอบ (TD-01), ปฏิทิน FY2027 เปิดงวด ม.ค.–ก.พ. 2027, กฎเลข JV{FY2}-{SEQ:6}, Workflow GL_JOURNAL 1 ขั้น (gl_accountant) | E46: 1. สร้าง Journal ประเภท 13 ค้างจ่าย/ค้างรับ วันที่ 31/01/2027 แล้ว Post 2. ดู Journal กลับรายการที่ระบบสร้าง | F46: 10-5100 Dr 75.25 / 10-2100 Cr 75.25 | G46: ระบบสร้าง Journal กลับรายการวันที่ 01/02/2027 สถานะ Unposted อ้างถึงรายการเดิม | I46: High | K46: Not Run
A47: TC-12-03 | B47: SC-12 | C47: กฎประเภท: วันถัดไป, กลับเครื่องหมาย, Post อัตโนมัติ (GL-106.6) | D47: ICC มีผังทดสอบ (TD-01), ปฏิทิน FY2027 เปิดงวด ม.ค.–ก.พ. 2027, กฎเลข JV{FY2}-{SEQ:6}, Workflow GL_JOURNAL 1 ขั้น (gl_accountant); System Admin สร้างประเภท DAILY_ACCRUAL ใน S06 | E47: 1. S06 สร้างประเภท DAILY_ACCRUAL รหัส Voucher 13 กลับรายการอัตโนมัติ: วันถัดไป, เปลี่ยนเครื่องหมาย, Post อัตโนมัติ 2. สร้าง Journal ประเภทนี้ 15/01/2027 แล้ว Post 3. ดูรายการกลับ และงบทดลอง ม.ค. | F47: 10-5100 Dr 75.25 / 10-2100 Cr 75.25 | G47: รายการกลับวันที่ 16/01/2027 สถานะ Posted ยอด -75.25 (10-5100 Dr -75.25, 10-2100 Cr -75.25); งบทดลอง ม.ค. ไม่มีบัญชี 10-5100 | I47: High | K47: Not Run
A48: TC-13-01 | B48: SC-13 | C48: Source บันทึกเอง (MANUAL) ต้องอนุมัติเสมอ | D48: ล็อกอินเป็น System Admin | E48: 1. S06 แท็บ Source ดู MANUAL และ PAYABLES 2. ปิด "ต้องอนุมัติ" ของ MANUAL | G48: MANUAL ต้องอนุมัติ, PAYABLES ไม่ต้อง; ข้อ 2 ไม่ยอม (P17) | I48: High | K48: Not Run
A49: TC-13-02 | B49: SC-13 | C49: สร้าง/ปิดประเภท Journal | D49: ล็อกอินเป็น System Admin | E49: 1. สร้างประเภท INDIRECT ค่าใช้จ่ายทางอ้อม รหัส Voucher 16 2. สร้าง INDIRECT ซ้ำ 3. ผู้จัดทำ (ไม่ใช่ Admin) ลองสร้างประเภท 4. ปิดใช้งาน INDIRECT แล้วสร้าง Journal ประเภทนี้ | F49: INDIRECT / Indirect charge / 16 | G49: ข้อ 1 สร้างได้ ใช้งาน ไม่กลับรายการอัตโนมัติ; ข้อ 2 แจ้งซ้ำ; ข้อ 3 ไม่มีสิทธิ์; ข้อ 4 แจ้งว่าประเภทปิดใช้งาน | I49: High | K49: Not Run
A50: TC-13-03 | B50: SC-13 | C50: เลข Voucher ICC {JC}{YY}{MM}{SEQ} เริ่มใหม่ทุกเดือนต่อประเภท | D50: ICC มีผังทดสอบ (TD-01), ปฏิทิน FY2027 เปิดงวด ม.ค.–ก.พ. 2027, กฎเลข JV{FY2}-{SEQ:6}, Workflow GL_JOURNAL 1 ขั้น (gl_accountant); S04 แก้กฎเลข GL_JOURNAL เป็น {JC}{YY}{MM}{SEQ:3} รีเซ็ตรายเดือน | E50: 1. Complete Journal ปรับปรุง ม.ค. 2 ฉบับ 2. Complete Journal ค้างจ่าย 31/01/2027 3. Complete Journal ปรับปรุง 03/02/2027 4. Complete Journal ประเภท จัดประเภทใหม่ (ไม่มีรหัส Voucher) | G50: ได้เลข 112701001, 112701002, 132701001, 112702001; ข้อ 4 แจ้งว่าประเภทต้องมีรหัส Voucher | I50: High | K50: Not Run
A51: TC-14-01 | B51: SC-14 | C51: ค้นหา Journal ตามงวด, Source, ประเภท, Batch | D51: Journal ม.ค. (Batch "2701 ปรับปรุงสิ้นเดือน", อ้างอิง REF-1) และ Journal ค้างจ่าย ก.พ. | E51: 1. ค้นหางวด FY2027-01, FY2027-02 2. ค้นหาประเภท ค้างจ่าย 3. ค้นหา Source MANUAL และ PAYABLES 4. ค้นหา Batch "2701" | G51: ผลลัพธ์: งวด ม.ค. 1, ก.พ. 1, ค้างจ่าย 1, MANUAL 2, PAYABLES 0, Batch 2701 = 1 | I51: Medium | K51: Not Run
A52: TC-14-02 | B52: SC-14 | C52: คัดลอก Journal (AutoCopy) | D52: ต่อจาก TC-14-01 | E52: 1. เปิด Journal ม.ค. กด คัดลอก วันที่ 28/02/2027 | G52: ได้ Journal ใหม่สถานะ Incomplete ไม่มีเลข วันที่ 28/02/2027 Source MANUAL Batch เดิม บรรทัด 10-5100 Dr 20 / 10-1100 Cr 20 | I52: Medium | K52: Not Run
A53: TC-14-03 | B53: SC-14 | C53: พิมพ์ Journal Voucher | D53: Journal Post แล้ว คำอธิบาย "ปรับปรุงค่าใช้จ่าย" 55.00 | E53: 1. เปิด Journal กด พิมพ์ Voucher | G53: Voucher แสดงบริษัท ICC เลข Journal สถานะ Posted ผู้จัดทำ icc.maker ผู้อนุมัติ/ผู้ Post icc.manager ประเภท ปรับปรุง Source บันทึกเอง และชื่อบัญชี "ค่าใช้จ่าย" | I53: Medium | K53: Not Run
A54: TC-15-01 | B54: SC-15 | C54: งบทดลองแยกบริษัท และยกยอดต้นงวด | D54: ICC Post ม.ค. 100.00 และ ก.พ. 20.00; ITK Post ม.ค. 999.00 | E54: 1. ล็อกอิน ICC เปิด CL04 งวด FY2027-02 | G54: แสดงเฉพาะ 10-1100, 10-5100; 10-5100 ยอดยกมา 100.00, Dr 20.00, ยอดปลาย 120.00; ไม่มียอด ITK | I54: High | K54: Not Run
A55: TC-15-02 | B55: SC-15 | C55: ผู้ใช้ ITK เปิด Journal ของ ICC ไม่ได้ | D55: ต่อจาก TC-15-01 | E55: 1. ล็อกอิน itk.maker เปิดลิงก์ Journal ของ ICC | G55: ไม่พบเอกสาร | I55: High | K55: Not Run
A56: TC-15-03 | B56: SC-15 | C56: Account Inquiry ผูกกับ Journal ที่ Post | D56: ต่อจาก TC-15-01 | E56: 1. เปิด GL-AI เลือกบัญชี 10-5100 งวด FY2027-01 | G56: แสดงรายการ JV27-000001 Dr 100.00 และยอดงวด ม.ค. Dr 100.00 ยอดปลาย 100.00 | I56: High | K56: Not Run
A57: TC-15-04 | B57: SC-15 | C57: เฉพาะ GL accountant ของบริษัทที่เลือกบันทึก Journal ได้ | D57: ผู้ใช้ clerk | E57: 1. clerk ไม่เลือกบริษัท สร้าง Journal 2. ให้ clerk มีบทบาท receiver ของ ICC เลือกบริษัท ICC แล้วสร้าง Journal | G57: ข้อ 1 แจ้งให้เลือกบริษัท; ข้อ 2 ไม่มีสิทธิ์ | I57: High | K57: Not Run
A58: TC-16-01 | B58: SC-16 | C58: ขอเปิดใช้ USD: ระหว่างรออนุมัติยังใช้ไม่ได้ | D58: ICC มีผังทดสอบ (TD-01), ปฏิทิน FY2027 เปิดงวด ม.ค.–ก.พ. 2027, กฎเลข JV{FY2}-{SEQ:6}, Workflow GL_JOURNAL 1 ขั้น (gl_accountant); Workflow GL_CURRENCY 1 ขั้น; ล็อกอินเป็น ผู้จัดทำ (Maker: gl_accountant) | E58: 1. เปิด /gl/currencies ดูสกุลเงิน 2. กด + ขอเปิดใช้สกุลเงิน USD 3. สร้าง Journal สกุล USD | F58: เหตุผล: เริ่มซื้อขายสกุลนี้ | G58: ตอนแรกเปิดใช้เฉพาะ THB; คำขอสถานะ รออนุมัติ USD ยังไม่เปิด; Journal USD แจ้งว่าสกุลเงินยังไม่เปิดใช้ | I58: High | K58: Not Run
A59: TC-16-02 | B59: SC-16 | C59: อนุมัติแล้ว USD เปิดใช้ | D59: ต่อจาก TC-16-01 | E59: 1. ผู้จัดทำลองอนุมัติเองใน H02 2. ผู้จัดการอนุมัติ 3. ดูรายการสกุลเงินและคำขอ | G59: ข้อ 1 ไม่ยอม (D07); หลังอนุมัติ USD เปิดใช้ คำขอสถานะ ใช้แล้ว | I59: High | K59: Not Run
A60: TC-16-03 | B60: SC-16 | C60: คำขอซ้ำ หรือสกุลที่ไม่มี | D60: ต่อจาก TC-16-02 | E60: 1. ขอเปิด USD อีกครั้ง 2. ขอเปิดสกุล XXX | G60: ข้อ 1 แจ้งซ้ำ; ข้อ 2 แจ้งว่าไม่มีสกุลนี้ | I60: High | K60: Not Run
A61: TC-17-01 | B61: SC-17 | C61: คีย์อัตราเอง วันเดียวกันแทนค่าเดิม | D61: USD เปิดใช้แล้ว; ล็อกอินเป็นผู้จัดทำ | E61: 1. กด + คีย์อัตรา USD CORPORATE 15/01/2027 = 35.125 2. คีย์ซ้ำวันเดียวกัน = 35.25 3. ค้นหาอัตรา USD | F61: อัตราทดสอบ (P08) | G61: มีแถวเดียว USD→THB CORPORATE 15/01/2027 อัตรา 35.250000 ที่มา MANUAL | I61: High | K61: Not Run
A62: TC-17-02 | B62: SC-17 | C62: ตรวจอัตราที่ผิด | D62: ต่อจาก TC-17-01 | E62: 1. คีย์อัตรา EUR ประเภท USER อัตรา 0 | F62: EUR ยังไม่เปิด | G62: แจ้ง EUR ยังไม่เปิดใช้ และประเภท USER คีย์เป็นอัตรารายวันไม่ได้ | I62: High | K62: Not Run
A63: TC-17-03 | B63: SC-17 | C63: ผู้ที่ไม่ใช่ GL accountant คีย์อัตราไม่ได้ | D63: ผู้ใช้ outsider | E63: 1. ล็อกอิน outsider คีย์อัตรา USD | G63: ไม่มีสิทธิ์ | I63: High | K63: Not Run
A64: TC-17-04 | B64: SC-17 | C64: นำเข้า Excel ที่มีแถวผิด ไม่บันทึกทั้งไฟล์ | D64: USD และ JPY เปิดใช้แล้ว | E64: 1. กด นำเข้าจาก Excel (GL_DAILY_RATES) ดาวน์โหลด Template 2. ใส่ข้อมูล TD-04 ชุดผิด แล้วอัปโหลด กด Load และ Import 3. ดูแถวผิด | F64: TD-04 ชุดผิด (6 แถว) | G64: ไม่มีอัตราใดถูกบันทึก; แถวผิดระบุคอลัมน์: แถว 3 FROM_CURRENCY, 4 RATE_TYPE, 5 RATE, 6–7 RATE_DATE (ซ้ำ) | I64: High | K64: Not Run
A65: TC-17-05 | B65: SC-17 | C65: นำเข้า Excel ที่ถูกต้อง | D65: ต่อจาก TC-17-04 | E65: 1. อัปโหลด TD-04 ชุดถูก กด Load และ Import | F65: TD-04 ชุดถูก (2 แถว) | G65: ประมวลผล 2 แถว ผิด 0; อัตรา USD 35.500000 และ JPY 0.235000 ที่มา IMPORT | I65: High | K65: Not Run
A66: TC-17-06 | B66: SC-17 | C66: ดึงอัตราจากธนาคาร (จำลอง D03) | D66: USD เปิดใช้; ฝั่งเซิร์ฟเวอร์ตั้ง BANK_RATE_SIM_FILE (ผู้ดูแลระบบ) | E66: 1. ก่อนตั้งค่า: กด ดึงจากธนาคาร (จำลอง) วันที่ 15/01/2027 2. หลังตั้งไฟล์จำลอง: กดอีกครั้ง | F66: ไฟล์จำลอง TD-05 | G66: ข้อ 1 แจ้งว่ายังไม่ได้ตั้งค่า; ข้อ 2 โหลด 1 รายการ ข้าม EUR; อัตรา USD 35.750000 ที่มา BANK_SIM | I66: High | K66: Not Run
A67: TC-18-01 | B67: SC-18 | C67: ไม่มีอัตราของวันที่ Complete ไม่ได้ | D67: USD เปิดใช้; ยังไม่มีอัตรา 15/01/2027 | E67: 1. สร้าง Journal USD CORPORATE 15/01/2027 ตามข้อมูล 2. กด Complete | F67: 10-5100 Dr 0.10 10-5100 Dr 0.10 10-1100 Cr 0.20 | G67: บันทึกร่างได้ (ยอด USD 0.20/0.20); Complete แจ้งที่วันที่อัตราว่าไม่มีอัตรา | I67: High | K67: Not Run
A68: TC-18-02 | B68: SC-18 | C68: ยังไม่ตั้งบัญชีปัดเศษ Complete ไม่ได้ | D68: ต่อจาก TC-18-01; คีย์อัตรา USD 15/01/2027 = 35.125 | E68: 1. กด Complete อีกครั้ง | G68: แจ้งว่ายังไม่ได้ตั้งบัญชีผลต่างจากการปัดเศษ | I68: High | K68: Not Run
A69: TC-18-03 | B69: SC-18 | C69: แปลงเป็นบาทและลงผลต่างปัดเศษ | D69: ต่อจาก TC-18-02 | E69: 1. /gl/currencies ตั้งบัญชี: ปัดเศษ 10-5300, กำไร 10-4100, ขาดทุน 10-5200 2. กด Complete 3. Submit, อนุมัติ, Post 4. ดูงบทดลอง FY2027-01 | F69: 0.10 × 35.125 = 3.5125 → 3.51; 0.20 × 35.125 = 7.025 → 7.03 | G69: อัตรา 35.125000 ยอดบาท 7.03/7.03; บรรทัด 3.51, 3.51, 7.03 และบรรทัดปัดเศษ 10-5300 Dr 0.01; งบทดลอง 10-1100 -7.03, 10-5100 7.02, 10-5300 0.01 | I69: High | K69: Not Run
A70: TC-18-04 | B70: SC-18 | C70: กลับรายการ Journal สกุลต่างประเทศ | D70: ต่อจาก TC-18-03 | E70: 1. กลับรายการวันที่ 20/01/2027 | G70: Journal ใหม่ USD อัตรา 35.125000 Unposted สลับฝั่งทั้งยอด USD และบาท รวมบรรทัดปัดเศษ (Cr 0.01) | I70: High | K70: Not Run
A71: TC-18-05 | B71: SC-18 | C71: ตรวจสมดุลที่ยอดสกุลเงินที่บันทึก | D71: USD เปิดใช้ ตั้งบัญชีแล้ว | E71: 1. Journal USD: 10-5100 Dr 10.00 / 10-1100 Cr 9.00 2. กด Complete | G71: แจ้งว่า Journal ไม่สมดุล | I71: High | K71: Not Run
A72: TC-18-06 | B72: SC-18 | C72: อัตราประเภท USER | D72: ต่อจาก TC-18-05 | E72: 1. Journal USD ประเภท USER ไม่ใส่อัตรา 2. Journal USD ประเภท CORPORATE ใส่อัตรา 35 3. Journal USD ประเภท USER อัตรา 36.5: Dr 10.00 / Cr 10.00 กด Complete | G72: ข้อ 1 และ 2 ไม่ยอม; ข้อ 3 อัตรา 36.500000 ยอดบาท 365.00 | I72: High | K72: Not Run
A73: TC-18-07 | B73: SC-18 | C73: JPY ไม่มีทศนิยม | D73: JPY เปิดใช้; อัตรา JPY 15/01/2027 = 0.235 | E73: 1. Journal JPY: 10-5100 Dr 100.50 / 10-1100 Cr 100.50 2. กด Complete | G73: แจ้งบรรทัด 1 และ 2 ว่าทศนิยมเกินที่สกุลเงินกำหนด | I73: High | K73: Not Run
A74: TC-18-08 | B74: SC-18 | C74: Journal บาท อัตรา 1 | E74: 1. Journal THB: 10-5100 Dr 5.00 / 10-1100 Cr 5.00 กด Complete | G74: สกุล THB อัตรา 1.000000 ยอดบาท = ยอดที่บันทึก = 5.00 | I74: High | K74: Not Run
A75: TC-19-01 | B75: SC-19 | C75: ไม่มีอัตราวันสิ้นงวด ปรับมูลค่าไม่ได้ | D75: USD เปิดใช้ ตั้งบัญชีแล้ว; อัตรา 15/01/2027 = 35; Post Journal USD ตามข้อมูล | E75: 1. /gl/currencies ส่วน Revaluation เลือกงวด FY2027-01 ประเภท CORPORATE 2. กด สร้าง Journal ปรับมูลค่า | F75: 10-1100 Dr 100.00 10-2100 Cr 40.00 10-5100 Cr 60.00 | G75: แจ้งว่าไม่มีอัตรา | I75: High | K75: Not Run
A76: TC-19-02 | B76: SC-19 | C76: สร้าง Journal ปรับมูลค่า ครั้งเดียวต่องวด | D76: ต่อจาก TC-19-01; คีย์อัตรา 31/01/2027 = 36 | E76: 1. กด สร้าง Journal ปรับมูลค่า 2. กดซ้ำอีกครั้ง | F76: เงินฝาก +100 บาท (กำไร), เจ้าหนี้ +40 บาท (ขาดทุน), ค่าใช้จ่ายไม่ปรับ | G76: Journal Source REVALUATION สกุล THB วันที่ 31/01/2027 Unposted ยอด 140.00: 10-1100 Dr 100, 10-2100 Cr 40, 10-4100 Cr 100, 10-5200 Dr 40; ข้อ 2 แจ้งว่าปรับมูลค่างวดนี้แล้ว | I76: High | K76: Not Run
A77: TC-19-03 | B77: SC-19 | C77: Post แล้วกลับรายการอัตโนมัติวันแรกของงวดถัดไป | D77: ต่อจาก TC-19-02 | E77: 1. ผู้จัดการ Post (ไม่ต้องอนุมัติ) 2. ดูรายการกลับ 3. งบทดลอง FY2027-01 และ FY2027-02 | G77: รายการกลับวันที่ 01/02/2027 Posted; ม.ค.: 10-1100 3,600.00, 10-2100 -1,440.00, 10-4100 -100.00, 10-5100 -2,100.00, 10-5200 40.00; ก.พ.: 10-1100 3,500.00, 10-2100 -1,400.00, 10-4100 0.00, 10-5100 -2,100.00, 10-5200 0.00 | I77: High | K77: Not Run

Sheet Test Data
A1: ชุดข้อมูลทดสอบ
A2: ค่าทั้งหมดเป็นข้อมูลสังเคราะห์สำหรับทดสอบ ไม่ใช่ผังบัญชี อัตราแลกเปลี่ยน หรือข้อมูลบริษัทจริง (P08) ค่าจริงนำเข้าจาก Oracle EBS ภายหลัง
A4: รหัส | B4: ชุดข้อมูล | C4: รายละเอียด
A5: TD-01 | B5: ผังทดสอบ 3 segment (SC-01–SC-06) | C5: CO (Company, 2 หลัก) – CC (Cost center, 3) – ACC (Natural account, 6) CO: 10 ICC, 20 ITK CC: 000 ไม่ระบุ, 100 ขาย ACC: 110100 เงินสด (asset, กระทบยอด), 410100 รายได้ขาย (revenue, monthly_income = DIV-IN)
A6: TD-02 | B6: ผัง ICC 8 segment (SC-07) | C6: CO 4, DEPT 6, ACC 9, PROD 25 (default 0), IC 4 (default 0000), RES1–RES3 3 (default 000) ค่า: CO ICC, DEPT T00001, ACC 900000001 บัญชีทดสอบ (expense), PROD 0 / TEST BRAND A, IC 0000, RES1–3 000
A7: TD-03 | B7: ผังสำหรับ Journal (SC-09–SC-19) | C7: CO (2) – ACC (4) SC-09–15: 1100 เงินสด, 2100 ค่าใช้จ่ายค้างจ่าย, 5100 ค่าใช้จ่าย, 5000 หัวรวม (ห้ามลงบัญชี), 5900 ปิดใช้งาน SC-16–19: 1100 เงินฝากสกุลต่างประเทศ, 2100 เจ้าหนี้สกุลต่างประเทศ, 4100 กำไรอัตราแลกเปลี่ยนยังไม่เกิด, 5100 ค่าใช้จ่าย, 5200 ขาดทุนอัตราแลกเปลี่ยนยังไม่เกิด, 5300 ผลต่างปัดเศษ
A8: TD-04 | B8: ไฟล์นำเข้าอัตรา GL_DAILY_RATES (SC-17) | C8: ชุดผิด (FROM_CURRENCY, RATE_TYPE, RATE_DATE, RATE): USD CORPORATE 2027-01-15 35.5 EUR CORPORATE 2027-01-15 38 (EUR ไม่เปิด) USD USER 2027-01-15 35 (ประเภท USER) JPY CORPORATE 2027-01-15 -1 (ติดลบ) JPY SPOT 2027-01-15 0.25 JPY SPOT 2027-01-15 0.26 (ซ้ำ) ชุดถูก: USD CORPORATE 2027-01-15 35.5; JPY CORPORATE 2027-01-15 0.235
A9: TD-05 | B9: ไฟล์ธนาคารจำลอง (SC-17) | C9: {"rates":[{"date":"2027-01-15","currency":"USD","rate":"35.75"},{"date":"2027-01-15","currency":"EUR","rate":"38.1"},{"date":"2027-01-16","currency":"USD","rate":"35.8"}]}
A10: TD-06 | B10: ผู้ใช้และสิทธิ์ | C10: System Admin: ตั้งค่า S01–S06 ผู้จัดทำ (Maker: gl_accountant): icc.maker / gl.clerk ผู้จัดการ (Manager: gl_accountant + gl_reviewer): icc.manager / gl.manager itk.maker: gl_accountant ของ ITK clerk / outsider: ไม่มีสิทธิ์ GL
A11: TD-07 | B11: ปฏิทิน, เลขเอกสาร, Workflow | C11: ปฏิทินเริ่มเดือน 1 ปี FY2027; ม.ค.–ก.พ. เปิด, มี.ค. Future entry (SC-10), เม.ย. ยังไม่เปิด กฎเลข GL_JOURNAL: JV{FY2}-{SEQ:6} (SC-13 ใช้ {JC}{YY}{MM}{SEQ:3} รีเซ็ตรายเดือน) Workflow GL_JOURNAL, GL_CURRENCY, GL_ACCOUNT_REQUEST: 1 ขั้น บทบาท gl_accountant ยอดตั้งแต่ 0

Sheet Sign-off
B2: การรับรองผลการทดสอบ (UAT Sign-off)
B4: ="ผลทดสอบ: ผ่าน "&Cover!C20&" จาก "&Cover!C23&" รายการ, ไม่ผ่าน "&Cover!C21&", ติดขัด "&Cover!C22&", ยังไม่ทดสอบ "&Cover!C19 -> ผลทดสอบ: ผ่าน 0 จาก 72 รายการ, ไม่ผ่าน 0, ติดขัด 0, ยังไม่ทดสอบ 72
B5: ข้อสรุป: ☐ ผ่าน ยอมรับระบบ ☐ ผ่านแบบมีเงื่อนไข (ระบุ Defect ที่ค้าง) ☐ ไม่ผ่าน
B7: บทบาท | C7: ชื่อ - นามสกุล | D7: ตำแหน่ง | E7: ลายมือชื่อ | F7: วันที่
B8: ผู้ทดสอบ (Key User GL)
B9: ผู้จัดการฝ่ายบัญชี
B10: ผู้ตรวจสอบฝ่ายบัญชี
B11: ผู้ดูแลระบบ / ทีมพัฒนา
B12: ผู้อนุมัติโครงการ
B14: Defect ที่ค้าง / เงื่อนไขการยอมรับ:
